mygraph.so
mygraph-0.9.8.dist-info/DESCRIPTION.rst
mygraph-0.9.8.dist-info/METADATA
mygraph-0.9.8.dist-info/RECORD
mygraph-0.9.8.dist-info/WHEEL
mygraph-0.9.8.dist-info/metadata.json
mygraph-0.9.8.dist-info/top_level.txt
