Metadata-Version: 2.0
Name: mygraph
Version: 0.9.8
Summary: Python wrapper of C++ Time-dependent Hyperpath algorithm implementation, requires python-dev, boost_python, pqxx and hdf5 installed
Home-page: http://fukudalab.hypernav.mobi
Author: Jiangshan(Tonny) Ma
Author-email: tonny.achilles@gmail.com
License: MIT
Keywords: hyperpath
Platform: UNKNOWN
Classifier: Development Status :: 3 - Alpha
Classifier: Intended Audience :: Developers
Classifier: Topic :: Software Development :: Build Tools
Classifier: License :: OSI Approved :: MIT License
Classifier: Programming Language :: Python :: 2.7
